scpca/__init__.py
scpca/logger.py
scpca/models/__init__.py
scpca/models/dpca.py
scpca/models/scpca.py
scpca/pca.py
scpca/plots/__init__.py
scpca/plots/data.py
scpca/plots/factor_embedding.py
scpca/plots/helper.py
scpca/plots/loadings_heatmap.py
scpca/plots/loadings_scatter.py
scpca/plots/loadings_state.py
scpca/plots/qc.py
scpca/train/__init__.py
scpca/train/handler.py
scpca/train/local_handler.py
scpca/train/settings.py
scpca/train/wrapper.py
scpca/utils/__init__.py
scpca/utils/data.py
scpca/utils/design.py
scpca-0.3.3.dist-info/LICENSE
scpca-0.3.3.dist-info/WHEEL
scpca-0.3.3.dist-info/METADATA
scpca-0.3.3.dist-info/RECORD
