Metadata-Version: 2.1
Name: scpca
Version: 0.3.3
Summary: Single-cell PCA.
Author: Harald Vohringer
Author-email: harald.voeh@gmail.com
Requires-Python: >=3.8.1,<3.12
Classifier: Programming Language :: Python :: 3
Classifier: Programming Language :: Python :: 3.9
Classifier: Programming Language :: Python :: 3.10
Classifier: Programming Language :: Python :: 3.11
Provides-Extra: docs
Provides-Extra: notebook
Requires-Dist: Sphinx (<7.0.0) ; extra == "docs"
Requires-Dist: adjusttext (>=0.7.3,<0.8.0)
Requires-Dist: jupyter ; extra == "notebook"
Requires-Dist: nbsphinx (==0.8.9) ; extra == "docs"
Requires-Dist: pyro-ppl (<1.8.4)
Requires-Dist: scanpy (>=1.8.2)
Requires-Dist: sphinx-autodoc-typehints (==1.23.0) ; extra == "docs"
Requires-Dist: sphinx-autopackagesummary (>=1.3,<2.0) ; extra == "docs"
Requires-Dist: sphinx-book-theme (>=1.0.1,<2.0.0) ; extra == "docs"
Requires-Dist: sphinxcontrib-bibtex (>=2.6.1,<3.0.0) ; extra == "docs"
Requires-Dist: sphinxcontrib-napoleon (==0.7) ; extra == "docs"
Requires-Dist: torch (<2.0.0)
